{"cbba_game_id":2345340,"year":2024,"game_date":"2024-02-03","is_neutral":false,"teams":[{"name":"Southeast Missouri St.","score":55,"players":[{"name":"Rob Martin","bart_id":77042,"is_starter":true,"mins":23.6,"pts":8,"fgm":4,"fga":9,"fgm3":0,"fga3":3,"ftm":0,"fta":0,"reb":2,"orb":1,"drb":1,"ast":3,"stl":2,"blk":0,"tov":2,"pf":4,"plus_minus":-13},{"name":"Adam Larson","bart_id":74452,"is_starter":true,"mins":21.2,"pts":7,"fgm":2,"fga":2,"fgm3":2,"fga3":2,"ftm":1,"fta":2,"reb":0,"orb":0,"drb":0,"ast":0,"stl":0,"blk":0,"tov":1,"pf":0,"plus_minus":-16},{"name":"Josh Earley","bart_id":70307,"is_starter":true,"mins":17.7,"pts":3,"fgm":1,"fga":4,"fgm3":0,"fga3":0,"ftm":1,"fta":2,"reb":3,"orb":1,"drb":2,"ast":0,"stl":1,"blk":0,"tov":2,"pf":0,"plus_minus":-16},{"name":"Braxton Stacker","bart_id":77521,"is_starter":true,"mins":17.1,"pts":5,"fgm":2,"fga":6,"fgm3":1,"fga3":3,"ftm":0,"fta":0,"reb":2,"orb":1,"drb":1,"ast":0,"stl":1,"blk":0,"tov":0,"pf":3,"plus_minus":-17},{"name":"Aquan Smart","bart_id":74925,"is_starter":true,"mins":16,"pts":2,"fgm":1,"fga":6,"fgm3":0,"fga3":1,"ftm":0,"fta":0,"reb":2,"orb":0,"drb":2,"ast":2,"stl":0,"blk":0,"tov":0,"pf":2,"plus_minus":-12},{"name":"Marqueas Bell","bart_id":77809,"is_starter":false,"mins":20.9,"pts":11,"fgm":3,"fga":7,"fgm3":1,"fga3":2,"ftm":4,"fta":6,"reb":4,"orb":1,"drb":3,"ast":0,"stl":1,"blk":0,"tov":3,"pf":1,"plus_minus":-6},{"name":"TJ Biel","bart_id":77919,"is_starter":false,"mins":20,"pts":0,"fgm":0,"fga":5,"fgm3":0,"fga3":2,"ftm":0,"fta":0,"reb":4,"orb":3,"drb":1,"ast":0,"stl":0,"blk":1,"tov":1,"pf":1,"plus_minus":-12},{"name":"BJ Ward","bart_id":77999,"is_starter":false,"mins":19.8,"pts":11,"fgm":5,"fga":9,"fgm3":1,"fga3":4,"ftm":0,"fta":0,"reb":1,"orb":0,"drb":1,"ast":0,"stl":0,"blk":0,"tov":1,"pf":0,"plus_minus":-8},{"name":"Evan Eursher","bart_id":76756,"is_starter":false,"mins":19.1,"pts":8,"fgm":2,"fga":6,"fgm3":2,"fga3":5,"ftm":2,"fta":2,"reb":1,"orb":0,"drb":1,"ast":0,"stl":0,"blk":0,"tov":1,"pf":1,"plus_minus":-4},{"name":"David Idada","bart_id":76757,"is_starter":false,"mins":14.6,"pts":0,"fgm":0,"fga":0,"fgm3":0,"fga3":0,"ftm":0,"fta":0,"reb":1,"orb":0,"drb":1,"ast":0,"stl":1,"blk":0,"tov":0,"pf":0,"plus_minus":-2},{"name":"Mason Hanback","bart_id":77008,"is_starter":false,"mins":6.3,"pts":0,"fgm":0,"fga":1,"fgm3":0,"fga3":0,"ftm":0,"fta":0,"reb":0,"orb":0,"drb":0,"ast":0,"stl":0,"blk":0,"tov":0,"pf":1,"plus_minus":0},{"name":"Gavyn Elkamil","bart_id":75695,"is_starter":false,"mins":3.8,"pts":0,"fgm":0,"fga":0,"fgm3":0,"fga3":0,"ftm":0,"fta":0,"reb":0,"orb":0,"drb":0,"ast":0,"stl":0,"blk":0,"tov":0,"pf":0,"plus_minus":1}],"totals":{"fgm":20,"fga":55,"fgm3":7,"fga3":22,"ftm":8,"fta":12,"reb":20,"orb":7,"drb":13,"ast":5,"stl":6,"blk":1,"tov":11,"pf":13,"pts":55}},{"name":"Western Illinois","score":76,"players":[{"name":"Drew Cisse","bart_id":79324,"is_starter":true,"mins":31.2,"pts":10,"fgm":5,"fga":9,"fgm3":0,"fga3":0,"ftm":0,"fta":0,"reb":13,"orb":4,"drb":9,"ast":5,"stl":1,"blk":0,"tov":0,"pf":2,"plus_minus":25},{"name":"Quinlan Bennett","bart_id":72283,"is_starter":true,"mins":29.6,"pts":15,"fgm":7,"fga":9,"fgm3":0,"fga3":0,"ftm":1,"fta":2,"reb":2,"orb":1,"drb":1,"ast":1,"stl":2,"blk":1,"tov":0,"pf":1,"plus_minus":20},{"name":"Ryan Myers","bart_id":73241,"is_starter":true,"mins":28.7,"pts":10,"fgm":3,"fga":10,"fgm3":2,"fga3":7,"ftm":2,"fta":2,"reb":4,"orb":0,"drb":4,"ast":0,"stl":1,"blk":0,"tov":0,"pf":2,"plus_minus":25},{"name":"JJ Kalakon","bart_id":77557,"is_starter":true,"mins":27.8,"pts":15,"fgm":4,"fga":8,"fgm3":2,"fga3":4,"ftm":5,"fta":6,"reb":5,"orb":1,"drb":4,"ast":1,"stl":0,"blk":0,"tov":2,"pf":0,"plus_minus":17},{"name":"Jesiah West","bart_id":76645,"is_starter":true,"mins":26.3,"pts":10,"fgm":5,"fga":7,"fgm3":0,"fga3":0,"ftm":0,"fta":0,"reb":7,"orb":1,"drb":6,"ast":4,"stl":0,"blk":1,"tov":2,"pf":2,"plus_minus":18},{"name":"James Dent Jr.","bart_id":79322,"is_starter":false,"mins":23.1,"pts":10,"fgm":3,"fga":7,"fgm3":1,"fga3":3,"ftm":3,"fta":3,"reb":2,"orb":1,"drb":1,"ast":1,"stl":0,"blk":0,"tov":3,"pf":2,"plus_minus":13},{"name":"Tay Knox","bart_id":79319,"is_starter":false,"mins":17.1,"pts":4,"fgm":1,"fga":1,"fgm3":0,"fga3":0,"ftm":2,"fta":2,"reb":3,"orb":1,"drb":2,"ast":0,"stl":0,"blk":0,"tov":0,"pf":2,"plus_minus":10},{"name":"Braden Lamar","bart_id":73664,"is_starter":false,"mins":3.8,"pts":2,"fgm":1,"fga":1,"fgm3":0,"fga3":0,"ftm":0,"fta":0,"reb":0,"orb":0,"drb":0,"ast":0,"stl":0,"blk":0,"tov":0,"pf":0,"plus_minus":-7},{"name":"KJ Lee","bart_id":75380,"is_starter":false,"mins":3,"pts":0,"fgm":0,"fga":0,"fgm3":0,"fga3":0,"ftm":0,"fta":0,"reb":1,"orb":0,"drb":1,"ast":0,"stl":0,"blk":0,"tov":0,"pf":1,"plus_minus":-4},{"name":"De' Meiko Anderson","bart_id":76995,"is_starter":false,"mins":3,"pts":0,"fgm":0,"fga":1,"fgm3":0,"fga3":1,"ftm":0,"fta":0,"reb":0,"orb":0,"drb":0,"ast":1,"stl":2,"blk":0,"tov":1,"pf":0,"plus_minus":-4},{"name":"Jacksun Hamilton","bart_id":78557,"is_starter":false,"mins":3,"pts":0,"fgm":0,"fga":0,"fgm3":0,"fga3":0,"ftm":0,"fta":0,"reb":0,"orb":0,"drb":0,"ast":0,"stl":0,"blk":0,"tov":0,"pf":1,"plus_minus":-4},{"name":"Shay Davis","bart_id":79323,"is_starter":false,"mins":3,"pts":0,"fgm":0,"fga":2,"fgm3":0,"fga3":1,"ftm":0,"fta":0,"reb":1,"orb":1,"drb":0,"ast":0,"stl":0,"blk":0,"tov":0,"pf":0,"plus_minus":-4},{"name":"Dirin Birhiray","bart_id":76993,"is_starter":false,"mins":0.6,"pts":0,"fgm":0,"fga":0,"fgm3":0,"fga3":0,"ftm":0,"fta":0,"reb":0,"orb":0,"drb":0,"ast":0,"stl":0,"blk":0,"tov":0,"pf":0,"plus_minus":0}],"totals":{"fgm":29,"fga":55,"fgm3":5,"fga3":16,"ftm":13,"fta":15,"reb":38,"orb":10,"drb":28,"ast":13,"stl":6,"blk":2,"tov":8,"pf":13,"pts":76}}]}