{"bart_player_id":32614,"seasons":[{"year":2017,"team_name":"Denver","team_conference":"Sum","class":"Sr","raw_row":["Josiah Dunn","Denver","Sum",5,0.4,155.5,22.9,100,80.81,0,23.2,74,0,0,1,0,2,2,1,0,0,0,0,0,50,"Sr","6-2",22,0.255086,161.303,0,2017,32614,"Littleton, CO",null,1.00000001,2,2,0,0,"1.0000",null,0,0,null,null,109.421,112.986,0.0583145,0.81315,13.6764,16.3371,-2.66061,16.1689,"1.0000",14.3565,1.81233,"0.0000","0.2000","0.2000","0.2000","0.0000","0.0000","0.8000","Pure PG",0,"1995-01-10"],"games":5,"notes":"Pure PG","projection":0,"net_onoff":null},{"year":2015,"team_name":"Denver","team_conference":"Sum","class":"So","raw_row":["Josiah Dunn","Denver","Sum",5,0.2,0,0,0,0,0,100.2,0,0,0,0,0,0,0,0,0,0,0,0,0,0,"So","6-2",10,-0.195606,-6.57748,0,2015,32614,"Littleton, CO",null,"0.00000000",null,null,null,null,null,null,null,null,null,null,85.4583,90.3434,0.0812611,0.874541,-21.6411,-14.4576,-7.18348,-4.09319,"0.6000",-6.67803,2.58484,"0.0000","0.4000","0.4000","0.0000","0.0000","0.0000","0.0000","PF/C",0,"1995-01-10"],"games":5,"notes":"PF/C","projection":0,"net_onoff":null},{"year":2014,"team_name":"Denver","team_conference":"Sum","class":"N/A","raw_row":["Josiah Dunn","Denver","Sum",2,0.2,0,22.5,0,0,0,0,0,100,0,0,0,0,0,0,0,0,0,0,0,0,"N/A","-",10,-0.463415,-0.723262,0,2014,32614,"Littleton, CO",null,"0.00000000",null,null,null,null,null,null,null,null,null,null,117.881,117.6,0.0661513,0.209999,-27.6195,-24.5625,-3.05701,-30.1764,"1.5000",-17.65,-12.5264,"0.0000","0.0000","0.0000","0.0000","0.0000","0.0000","0.0000","PF/C",0,"1995-01-10"],"games":2,"notes":"PF/C","projection":0,"net_onoff":null}]}