{"bart_player_id":33883,"seasons":[{"year":2015,"team_name":"Miami OH","team_conference":"MAC","class":"Fr","raw_row":["Tre Hawkins","Miami OH","MAC",1,0.1,225.6,13.9,0,0,0,0,100,0,0,0,0,0,0,0,0,0,0,0,60.9,0,"Fr","5-10",20,0.395098,201.235,0,2015,33883,null,null,"1.00000000",null,null,null,null,null,null,null,null,null,null,-18.0009,-17.4897,0.509616,1.08871,43.5675,11.271,32.2965,95.8584,"1.0000",30.1341,65.7243,"0.0000","0.0000","0.0000","1.0000","1.0000","0.0000","0.0000","Pure PG",0,"1995-10-15"],"games":1,"notes":"Pure PG","projection":0}]}