{"cbba_game_id":2739682,"year":2026,"game_date":"2026-01-03","is_neutral":false,"teams":[{"name":"NJIT","score":73,"players":[{"name":"Jordan Rogers","bart_id":126737,"is_starter":true,"mins":32.6,"pts":0,"fgm":0,"fga":1,"fgm3":0,"fga3":0,"ftm":0,"fta":0,"reb":6,"orb":1,"drb":5,"ast":2,"stl":1,"blk":1,"tov":2,"pf":3,"plus_minus":5},{"name":"Melvyn Ebonkoli","bart_id":72726,"is_starter":true,"mins":31.6,"pts":16,"fgm":6,"fga":9,"fgm3":0,"fga3":0,"ftm":4,"fta":5,"reb":8,"orb":4,"drb":4,"ast":0,"stl":0,"blk":0,"tov":2,"pf":3,"plus_minus":3},{"name":"David Bolden","bart_id":134594,"is_starter":true,"mins":27.5,"pts":12,"fgm":3,"fga":10,"fgm3":2,"fga3":5,"ftm":4,"fta":7,"reb":4,"orb":1,"drb":3,"ast":3,"stl":2,"blk":0,"tov":3,"pf":3,"plus_minus":-3},{"name":"Ari Fulton","bart_id":128101,"is_starter":true,"mins":25.3,"pts":2,"fgm":1,"fga":4,"fgm3":0,"fga3":1,"ftm":0,"fta":0,"reb":2,"orb":0,"drb":2,"ast":0,"stl":2,"blk":0,"tov":0,"pf":4,"plus_minus":3},{"name":"Quentin Duncan","bart_id":128102,"is_starter":true,"mins":18.7,"pts":5,"fgm":2,"fga":7,"fgm3":1,"fga3":4,"ftm":0,"fta":1,"reb":1,"orb":1,"drb":0,"ast":0,"stl":1,"blk":0,"tov":0,"pf":1,"plus_minus":0},{"name":"Sebastian Robinson","bart_id":77990,"is_starter":false,"mins":29.7,"pts":22,"fgm":7,"fga":12,"fgm3":1,"fga3":2,"ftm":7,"fta":7,"reb":3,"orb":0,"drb":3,"ast":3,"stl":1,"blk":0,"tov":1,"pf":1,"plus_minus":17},{"name":"Jeremy Clayville","bart_id":127975,"is_starter":false,"mins":16.9,"pts":7,"fgm":3,"fga":5,"fgm3":1,"fga3":2,"ftm":0,"fta":0,"reb":1,"orb":0,"drb":1,"ast":0,"stl":0,"blk":0,"tov":0,"pf":0,"plus_minus":9},{"name":"John Kelly","bart_id":128100,"is_starter":false,"mins":10,"pts":5,"fgm":2,"fga":3,"fgm3":1,"fga3":2,"ftm":0,"fta":0,"reb":2,"orb":0,"drb":2,"ast":0,"stl":0,"blk":0,"tov":1,"pf":1,"plus_minus":4},{"name":"Malachi Arrington","bart_id":128099,"is_starter":false,"mins":6.4,"pts":4,"fgm":1,"fga":3,"fgm3":0,"fga3":0,"ftm":2,"fta":2,"reb":1,"orb":0,"drb":1,"ast":0,"stl":0,"blk":0,"tov":1,"pf":3,"plus_minus":3},{"name":"Rocco Awad","bart_id":133703,"is_starter":false,"mins":1.3,"pts":0,"fgm":0,"fga":0,"fgm3":0,"fga3":0,"ftm":0,"fta":0,"reb":0,"orb":0,"drb":0,"ast":0,"stl":0,"blk":0,"tov":0,"pf":0,"plus_minus":-1}],"totals":{"fgm":25,"fga":54,"fgm3":6,"fga3":16,"ftm":17,"fta":22,"reb":28,"orb":7,"drb":21,"ast":8,"stl":7,"blk":1,"tov":10,"pf":19,"pts":73}},{"name":"Binghamton","score":65,"players":[{"name":"Wes Peterson","bart_id":74991,"is_starter":true,"mins":36.9,"pts":8,"fgm":2,"fga":8,"fgm3":0,"fga3":1,"ftm":4,"fta":4,"reb":5,"orb":0,"drb":5,"ast":1,"stl":2,"blk":0,"tov":2,"pf":1,"plus_minus":-10},{"name":"Ryan Richardson","bart_id":134292,"is_starter":true,"mins":36.4,"pts":16,"fgm":6,"fga":10,"fgm3":3,"fga3":5,"ftm":1,"fta":3,"reb":0,"orb":0,"drb":0,"ast":4,"stl":0,"blk":0,"tov":3,"pf":1,"plus_minus":-9},{"name":"Jackson Benigni","bart_id":76867,"is_starter":true,"mins":31.5,"pts":9,"fgm":2,"fga":6,"fgm3":1,"fga3":5,"ftm":4,"fta":4,"reb":6,"orb":1,"drb":5,"ast":1,"stl":2,"blk":0,"tov":1,"pf":5,"plus_minus":-3},{"name":"Jeremiah Quigley","bart_id":77754,"is_starter":true,"mins":22.5,"pts":4,"fgm":2,"fga":4,"fgm3":0,"fga3":1,"ftm":0,"fta":1,"reb":4,"orb":1,"drb":3,"ast":5,"stl":1,"blk":0,"tov":3,"pf":5,"plus_minus":0},{"name":"Zyier Beverly","bart_id":134832,"is_starter":true,"mins":21.4,"pts":9,"fgm":2,"fga":3,"fgm3":0,"fga3":0,"ftm":5,"fta":6,"reb":3,"orb":0,"drb":3,"ast":0,"stl":2,"blk":0,"tov":0,"pf":4,"plus_minus":-9},{"name":"Bryson Wilson","bart_id":79147,"is_starter":false,"mins":29.4,"pts":15,"fgm":3,"fga":5,"fgm3":2,"fga3":3,"ftm":7,"fta":8,"reb":3,"orb":1,"drb":2,"ast":2,"stl":1,"blk":0,"tov":2,"pf":2,"plus_minus":-7},{"name":"Jake Blackburn","bart_id":133797,"is_starter":false,"mins":13.2,"pts":4,"fgm":2,"fga":3,"fgm3":0,"fga3":0,"ftm":0,"fta":0,"reb":0,"orb":0,"drb":0,"ast":0,"stl":0,"blk":0,"tov":0,"pf":0,"plus_minus":-2},{"name":"Stephan Snagg","bart_id":78388,"is_starter":false,"mins":8.2,"pts":0,"fgm":0,"fga":0,"fgm3":0,"fga3":0,"ftm":0,"fta":0,"reb":1,"orb":0,"drb":1,"ast":0,"stl":0,"blk":0,"tov":0,"pf":0,"plus_minus":0},{"name":"Nevin Ibroci","bart_id":127858,"is_starter":false,"mins":0.6,"pts":0,"fgm":0,"fga":0,"fgm3":0,"fga3":0,"ftm":0,"fta":0,"reb":0,"orb":0,"drb":0,"ast":0,"stl":0,"blk":0,"tov":0,"pf":0,"plus_minus":0}],"totals":{"fgm":19,"fga":39,"fgm3":6,"fga3":15,"ftm":21,"fta":26,"reb":22,"orb":3,"drb":19,"ast":13,"stl":8,"blk":0,"tov":11,"pf":18,"pts":65}}]}