{"cbba_game_id":2753419,"year":2026,"game_date":"2026-01-11","is_neutral":false,"teams":[{"name":"Ohio St.","score":74,"players":[{"name":"Bruce Thornton","bart_id":76969,"is_starter":true,"mins":36.7,"pts":28,"fgm":9,"fga":17,"fgm3":3,"fga3":7,"ftm":7,"fta":8,"reb":4,"orb":2,"drb":2,"ast":3,"stl":1,"blk":1,"tov":1,"pf":1,"plus_minus":-6},{"name":"Amare Bynum","bart_id":135542,"is_starter":true,"mins":36.5,"pts":20,"fgm":8,"fga":19,"fgm3":2,"fga3":6,"ftm":2,"fta":3,"reb":4,"orb":2,"drb":2,"ast":1,"stl":1,"blk":1,"tov":2,"pf":3,"plus_minus":-7},{"name":"Devin Royal","bart_id":79409,"is_starter":true,"mins":30.9,"pts":11,"fgm":4,"fga":9,"fgm3":1,"fga3":3,"ftm":2,"fta":2,"reb":8,"orb":1,"drb":7,"ast":1,"stl":0,"blk":0,"tov":1,"pf":3,"plus_minus":-7},{"name":"John Mobley Jr.","bart_id":126733,"is_starter":true,"mins":29.3,"pts":3,"fgm":1,"fga":5,"fgm3":1,"fga3":3,"ftm":0,"fta":0,"reb":4,"orb":1,"drb":3,"ast":4,"stl":1,"blk":0,"tov":3,"pf":1,"plus_minus":-6},{"name":"Christoph Tilly","bart_id":76887,"is_starter":true,"mins":15.3,"pts":8,"fgm":3,"fga":7,"fgm3":0,"fga3":1,"ftm":2,"fta":2,"reb":4,"orb":2,"drb":2,"ast":1,"stl":0,"blk":0,"tov":1,"pf":2,"plus_minus":-5},{"name":"Ivan Njegovan","bart_id":127337,"is_starter":false,"mins":24.6,"pts":4,"fgm":2,"fga":4,"fgm3":0,"fga3":0,"ftm":0,"fta":0,"reb":6,"orb":4,"drb":2,"ast":2,"stl":0,"blk":1,"tov":2,"pf":2,"plus_minus":-1},{"name":"Gabe Cupps","bart_id":77756,"is_starter":false,"mins":13.8,"pts":0,"fgm":0,"fga":0,"fgm3":0,"fga3":0,"ftm":0,"fta":0,"reb":1,"orb":1,"drb":0,"ast":1,"stl":0,"blk":0,"tov":0,"pf":2,"plus_minus":-4},{"name":"Colin White","bart_id":128091,"is_starter":false,"mins":7.8,"pts":0,"fgm":0,"fga":0,"fgm3":0,"fga3":0,"ftm":0,"fta":0,"reb":2,"orb":1,"drb":1,"ast":0,"stl":0,"blk":0,"tov":0,"pf":1,"plus_minus":0},{"name":"Taison Chatman","bart_id":79408,"is_starter":false,"mins":5.2,"pts":0,"fgm":0,"fga":2,"fgm3":0,"fga3":2,"ftm":0,"fta":0,"reb":2,"orb":1,"drb":1,"ast":1,"stl":1,"blk":0,"tov":0,"pf":2,"plus_minus":1}],"totals":{"fgm":27,"fga":63,"fgm3":7,"fga3":22,"ftm":13,"fta":15,"reb":35,"orb":15,"drb":20,"ast":14,"stl":4,"blk":3,"tov":10,"pf":17,"pts":74}},{"name":"Washington","score":81,"players":[{"name":"Hannes Steinbach","bart_id":135114,"is_starter":true,"mins":35.3,"pts":21,"fgm":9,"fga":19,"fgm3":0,"fga3":3,"ftm":3,"fta":3,"reb":9,"orb":1,"drb":8,"ast":0,"stl":2,"blk":0,"tov":3,"pf":3,"plus_minus":6},{"name":"Quimari Peterson","bart_id":74904,"is_starter":true,"mins":34.7,"pts":8,"fgm":2,"fga":5,"fgm3":2,"fga3":4,"ftm":2,"fta":2,"reb":2,"orb":0,"drb":2,"ast":3,"stl":1,"blk":0,"tov":1,"pf":2,"plus_minus":3},{"name":"Bryson Tucker","bart_id":127366,"is_starter":true,"mins":33.9,"pts":12,"fgm":6,"fga":11,"fgm3":0,"fga3":2,"ftm":0,"fta":0,"reb":5,"orb":3,"drb":2,"ast":2,"stl":0,"blk":1,"tov":0,"pf":2,"plus_minus":6},{"name":"Franck Kepnang","bart_id":74203,"is_starter":true,"mins":30.7,"pts":11,"fgm":2,"fga":3,"fgm3":0,"fga3":0,"ftm":7,"fta":8,"reb":7,"orb":4,"drb":3,"ast":0,"stl":1,"blk":2,"tov":2,"pf":4,"plus_minus":6},{"name":"Zoom Diallo","bart_id":126760,"is_starter":true,"mins":29.8,"pts":22,"fgm":7,"fga":14,"fgm3":2,"fga3":6,"ftm":6,"fta":6,"reb":2,"orb":0,"drb":2,"ast":3,"stl":0,"blk":0,"tov":0,"pf":1,"plus_minus":1},{"name":"JJ Mandaquit","bart_id":134321,"is_starter":false,"mins":16.1,"pts":1,"fgm":0,"fga":0,"fgm3":0,"fga3":0,"ftm":1,"fta":4,"reb":2,"orb":0,"drb":2,"ast":5,"stl":0,"blk":0,"tov":1,"pf":0,"plus_minus":4},{"name":"Nikola Dzepina","bart_id":143658,"is_starter":false,"mins":10.6,"pts":3,"fgm":1,"fga":3,"fgm3":1,"fga3":2,"ftm":0,"fta":0,"reb":0,"orb":0,"drb":0,"ast":0,"stl":0,"blk":3,"tov":0,"pf":0,"plus_minus":2},{"name":"Courtland Muldrew","bart_id":135560,"is_starter":false,"mins":9,"pts":3,"fgm":1,"fga":1,"fgm3":1,"fga3":1,"ftm":0,"fta":0,"reb":0,"orb":0,"drb":0,"ast":1,"stl":0,"blk":0,"tov":0,"pf":2,"plus_minus":7}],"totals":{"fgm":28,"fga":56,"fgm3":6,"fga3":18,"ftm":19,"fta":23,"reb":27,"orb":8,"drb":19,"ast":14,"stl":4,"blk":6,"tov":7,"pf":14,"pts":81}}]}