{"bartId":28701,"seasonRanks":[{"year":2016,"bucket":"F","cohortSize":336,"stats":{"pts_pg":{"value":12.1176,"percentile":72},"reb_pg":{"value":5.1765,"percentile":48},"ast_pg":{"value":0.8529,"percentile":30},"stl_pg":{"value":0.8529,"percentile":75},"blk_pg":{"value":0.2647,"percentile":27},"ortg":{"value":106.6,"percentile":56},"usage":{"value":21.4,"percentile":60},"efg_pct":{"value":53.4,"percentile":69},"ts_pct":{"value":56.55,"percentile":65},"orb_pct":{"value":6.5,"percentile":56},"drb_pct":{"value":14.3,"percentile":34},"ast_pct":{"value":6,"percentile":19},"tov_pct":{"value":14.9,"percentile":63},"ft_pct":{"value":0.722,"percentile":49},"fg2_pct":{"value":0.524,"percentile":66},"fg3_pct":{"value":0.372,"percentile":70},"blk_pct":{"value":0.9,"percentile":18},"stl_pct":{"value":1.7,"percentile":71},"hkm_pct":{"value":2.6,"percentile":33},"ftr":{"value":34.5,"percentile":54},"porpag":{"value":2.0193,"percentile":62},"pir":{"value":19.104566,"percentile":66},"bta_portg":{"value":13.030780635535466,"percentile":59}}}]}