{"bartId":51308,"seasonRanks":[{"year":2019,"bucket":"G","cohortSize":1237,"stats":{"pts_pg":{"value":15.2727,"percentile":85},"reb_pg":{"value":2.7879,"percentile":34},"ast_pg":{"value":5.8182,"percentile":98},"stl_pg":{"value":2.8485,"percentile":100},"blk_pg":{"value":0.1212,"percentile":42},"ortg":{"value":107.2,"percentile":67},"usage":{"value":26.5,"percentile":89},"efg_pct":{"value":49.9,"percentile":50},"ts_pct":{"value":54.57,"percentile":58},"orb_pct":{"value":1.1,"percentile":12},"drb_pct":{"value":8.6,"percentile":24},"ast_pct":{"value":34,"percentile":98},"tov_pct":{"value":22.8,"percentile":13},"ft_pct":{"value":0.813,"percentile":76},"fg2_pct":{"value":0.504,"percentile":70},"fg3_pct":{"value":0.327,"percentile":34},"blk_pct":{"value":0.4,"percentile":36},"stl_pct":{"value":5,"percentile":100},"hkm_pct":{"value":5.4,"percentile":97},"ftr":{"value":31.9,"percentile":57},"porpag":{"value":3.79486,"percentile":93},"pir":{"value":24.194190000000003,"percentile":85},"bta_portg":{"value":39.5994434754398,"percentile":96}}},{"year":2018,"bucket":"G","cohortSize":1245,"stats":{"pts_pg":{"value":15.9091,"percentile":86},"reb_pg":{"value":3.3636,"percentile":53},"ast_pg":{"value":5.9697,"percentile":98},"stl_pg":{"value":2.0606,"percentile":98},"blk_pg":{"value":0.0909,"percentile":31},"ortg":{"value":110.4,"percentile":73},"usage":{"value":27.5,"percentile":92},"efg_pct":{"value":50.6,"percentile":53},"ts_pct":{"value":55.57,"percentile":62},"orb_pct":{"value":1.1,"percentile":11},"drb_pct":{"value":10.8,"percentile":52},"ast_pct":{"value":33.7,"percentile":97},"tov_pct":{"value":18.8,"percentile":37},"ft_pct":{"value":0.801,"percentile":68},"fg2_pct":{"value":0.485,"percentile":59},"fg3_pct":{"value":0.351,"percentile":46},"blk_pct":{"value":0.3,"percentile":26},"stl_pct":{"value":3.6,"percentile":97},"hkm_pct":{"value":3.9,"percentile":86},"ftr":{"value":36.2,"percentile":68},"porpag":{"value":4.26724,"percentile":95},"pir":{"value":27.145605000000003,"percentile":92},"bta_portg":{"value":46.26559075822262,"percentile":98}}}]}