{"bartId":74655,"seasonRanks":[{"year":2025,"bucket":"C","cohortSize":321,"stats":{"pts_pg":{"value":13.3333,"percentile":84},"reb_pg":{"value":6.6667,"percentile":59},"ast_pg":{"value":3.1111,"percentile":98},"stl_pg":{"value":0.7407,"percentile":64},"blk_pg":{"value":0.8519,"percentile":43},"ortg":{"value":101.7,"percentile":14},"usage":{"value":29.1,"percentile":97},"efg_pct":{"value":53.5,"percentile":28},"ts_pct":{"value":54.61,"percentile":21},"orb_pct":{"value":6.8,"percentile":9},"drb_pct":{"value":21.4,"percentile":69},"ast_pct":{"value":28.2,"percentile":100},"tov_pct":{"value":19.6,"percentile":22},"ft_pct":{"value":0.583,"percentile":28},"fg2_pct":{"value":0.553,"percentile":33},"fg3_pct":{"value":0.258,"percentile":62},"blk_pct":{"value":3.4,"percentile":31},"stl_pct":{"value":1.6,"percentile":58},"hkm_pct":{"value":5,"percentile":32},"ftr":{"value":33.8,"percentile":23},"porpag":{"value":2.03382,"percentile":54},"pir":{"value":23.186333,"percentile":89},"bta_portg":{"value":17.96317336494201,"percentile":73}}},{"year":2024,"bucket":"C","cohortSize":349,"stats":{"pts_pg":{"value":10.7586,"percentile":64},"reb_pg":{"value":7.8621,"percentile":80},"ast_pg":{"value":3.6897,"percentile":99},"stl_pg":{"value":0.6897,"percentile":64},"blk_pg":{"value":1.0345,"percentile":56},"ortg":{"value":98,"percentile":10},"usage":{"value":26.3,"percentile":90},"efg_pct":{"value":52,"percentile":21},"ts_pct":{"value":51.48,"percentile":10},"orb_pct":{"value":7.1,"percentile":12},"drb_pct":{"value":25,"percentile":90},"ast_pct":{"value":26.8,"percentile":99},"tov_pct":{"value":22.5,"percentile":10},"ft_pct":{"value":0.462,"percentile":5},"fg2_pct":{"value":0.544,"percentile":34},"fg3_pct":{"value":0.118,"percentile":44},"blk_pct":{"value":4.4,"percentile":53},"stl_pct":{"value":1.3,"percentile":40},"hkm_pct":{"value":5.7,"percentile":47},"ftr":{"value":35.8,"percentile":30},"porpag":{"value":1.75395,"percentile":46},"pir":{"value":21.214740000000003,"percentile":81},"bta_portg":{"value":13.872937205544302,"percentile":63}}},{"year":2023,"bucket":"C","cohortSize":339,"stats":{"pts_pg":{"value":8.7667,"percentile":43},"reb_pg":{"value":5.5667,"percentile":38},"ast_pg":{"value":3.0667,"percentile":97},"stl_pg":{"value":0.7333,"percentile":70},"blk_pg":{"value":0.4333,"percentile":14},"ortg":{"value":92.1,"percentile":4},"usage":{"value":29.4,"percentile":95},"efg_pct":{"value":50.9,"percentile":20},"ts_pct":{"value":50.55,"percentile":10},"orb_pct":{"value":10.6,"percentile":61},"drb_pct":{"value":17.5,"percentile":34},"ast_pct":{"value":28.5,"percentile":99},"tov_pct":{"value":27.6,"percentile":1},"ft_pct":{"value":0.458,"percentile":4},"fg2_pct":{"value":0.533,"percentile":28},"fg3_pct":{"value":0,"percentile":11},"blk_pct":{"value":2.4,"percentile":20},"stl_pct":{"value":2,"percentile":82},"hkm_pct":{"value":4.4,"percentile":32},"ftr":{"value":32.7,"percentile":24},"porpag":{"value":1.13157,"percentile":22},"pir":{"value":16.06737,"percentile":52},"bta_portg":{"value":5.452946229131666,"percentile":32}}}]}