{"bartId":75629,"seasonRanks":[{"year":2023,"bucket":"G","cohortSize":1302,"stats":{"pts_pg":{"value":13.2414,"percentile":75},"reb_pg":{"value":3.8276,"percentile":68},"ast_pg":{"value":4,"percentile":89},"stl_pg":{"value":1.5172,"percentile":87},"blk_pg":{"value":0.1724,"percentile":54},"ortg":{"value":93.7,"percentile":15},"usage":{"value":28.6,"percentile":95},"efg_pct":{"value":43.6,"percentile":14},"ts_pct":{"value":47.44,"percentile":13},"orb_pct":{"value":3,"percentile":66},"drb_pct":{"value":11.3,"percentile":54},"ast_pct":{"value":32.6,"percentile":97},"tov_pct":{"value":20.7,"percentile":20},"ft_pct":{"value":0.756,"percentile":44},"fg2_pct":{"value":0.43,"percentile":28},"fg3_pct":{"value":0.299,"percentile":20},"blk_pct":{"value":0.6,"percentile":46},"stl_pct":{"value":3,"percentile":88},"hkm_pct":{"value":3.6,"percentile":77},"ftr":{"value":24.9,"percentile":40},"porpag":{"value":1.9149,"percentile":60},"pir":{"value":21.176946999999995,"percentile":75},"bta_portg":{"value":21.494647514587427,"percentile":79}}},{"year":2022,"bucket":"G","cohortSize":1282,"stats":{"pts_pg":{"value":14.4839,"percentile":84},"reb_pg":{"value":4.871,"percentile":86},"ast_pg":{"value":4.129,"percentile":92},"stl_pg":{"value":1.5806,"percentile":89},"blk_pg":{"value":0.5484,"percentile":94},"ortg":{"value":101.2,"percentile":46},"usage":{"value":29.8,"percentile":97},"efg_pct":{"value":50.5,"percentile":61},"ts_pct":{"value":52.96,"percentile":53},"orb_pct":{"value":3.5,"percentile":72},"drb_pct":{"value":16.1,"percentile":91},"ast_pct":{"value":31.4,"percentile":96},"tov_pct":{"value":21.5,"percentile":17},"ft_pct":{"value":0.7,"percentile":24},"fg2_pct":{"value":0.498,"percentile":68},"fg3_pct":{"value":0.348,"percentile":55},"blk_pct":{"value":2.3,"percentile":95},"stl_pct":{"value":3.3,"percentile":92},"hkm_pct":{"value":5.6,"percentile":97},"ftr":{"value":24.5,"percentile":41},"porpag":{"value":2.8616,"percentile":80},"pir":{"value":21.53654,"percentile":77},"bta_portg":{"value":23.224660331471558,"percentile":82}}}]}