{"cbba_game_id":1519798,"year":2013,"game_date":"2012-12-22","is_neutral":false,"teams":[{"name":"Davidson","score":58,"players":[{"name":"Nik Cochran","bart_id":13358,"is_starter":true,"mins":32,"pts":10,"fgm":3,"fga":6,"fgm3":0,"fga3":2,"ftm":4,"fta":4,"reb":3,"orb":1,"drb":2,"ast":4,"stl":0,"blk":0,"tov":2,"pf":1,"plus_minus":null},{"name":"De'Mon Brooks","bart_id":15850,"is_starter":true,"mins":30,"pts":16,"fgm":5,"fga":9,"fgm3":2,"fga3":5,"ftm":4,"fta":4,"reb":3,"orb":1,"drb":2,"ast":1,"stl":1,"blk":2,"tov":3,"pf":4,"plus_minus":null},{"name":"Jake Cohen","bart_id":13359,"is_starter":true,"mins":27,"pts":10,"fgm":4,"fga":9,"fgm3":1,"fga3":5,"ftm":1,"fta":2,"reb":0,"orb":0,"drb":0,"ast":1,"stl":0,"blk":0,"tov":1,"pf":2,"plus_minus":null},{"name":"Jp Kuhlman","bart_id":10974,"is_starter":true,"mins":25,"pts":1,"fgm":0,"fga":2,"fgm3":0,"fga3":0,"ftm":1,"fta":2,"reb":0,"orb":0,"drb":0,"ast":1,"stl":3,"blk":0,"tov":2,"pf":2,"plus_minus":null},{"name":"Chris Czerapowicz","bart_id":15852,"is_starter":true,"mins":21,"pts":8,"fgm":3,"fga":6,"fgm3":2,"fga3":3,"ftm":0,"fta":0,"reb":2,"orb":0,"drb":2,"ast":0,"stl":0,"blk":0,"tov":1,"pf":1,"plus_minus":null},{"name":"Tyler Kalinoski","bart_id":20132,"is_starter":false,"mins":27,"pts":9,"fgm":3,"fga":7,"fgm3":3,"fga3":7,"ftm":0,"fta":2,"reb":1,"orb":0,"drb":1,"ast":0,"stl":1,"blk":0,"tov":0,"pf":2,"plus_minus":null},{"name":"Clint Mann","bart_id":14932,"is_starter":false,"mins":16,"pts":0,"fgm":0,"fga":2,"fgm3":0,"fga3":0,"ftm":0,"fta":0,"reb":0,"orb":0,"drb":0,"ast":1,"stl":0,"blk":0,"tov":0,"pf":4,"plus_minus":null},{"name":"Tom Droney","bart_id":15849,"is_starter":false,"mins":16,"pts":4,"fgm":1,"fga":1,"fgm3":0,"fga3":0,"ftm":2,"fta":2,"reb":3,"orb":2,"drb":1,"ast":2,"stl":1,"blk":0,"tov":0,"pf":0,"plus_minus":null},{"name":"Jake Belford","bart_id":24263,"is_starter":false,"mins":3,"pts":0,"fgm":0,"fga":0,"fgm3":0,"fga3":0,"ftm":0,"fta":0,"reb":1,"orb":0,"drb":1,"ast":0,"stl":0,"blk":0,"tov":0,"pf":0,"plus_minus":null},{"name":"Jordan Barham","bart_id":24580,"is_starter":false,"mins":3,"pts":0,"fgm":0,"fga":1,"fgm3":0,"fga3":0,"ftm":0,"fta":0,"reb":0,"orb":0,"drb":0,"ast":0,"stl":0,"blk":0,"tov":0,"pf":1,"plus_minus":null}],"totals":{"fgm":19,"fga":43,"fgm3":8,"fga3":22,"ftm":12,"fta":16,"reb":13,"orb":4,"drb":9,"ast":10,"stl":6,"blk":2,"tov":9,"pf":17,"pts":58}},{"name":"Drexel","score":69,"players":[{"name":"Derrick Thomas","bart_id":13679,"is_starter":true,"mins":38,"pts":9,"fgm":3,"fga":5,"fgm3":1,"fga3":3,"ftm":2,"fta":2,"reb":2,"orb":0,"drb":2,"ast":3,"stl":0,"blk":0,"tov":1,"pf":1,"plus_minus":null},{"name":"Frantz Massenat","bart_id":19215,"is_starter":true,"mins":36,"pts":14,"fgm":6,"fga":13,"fgm3":2,"fga3":5,"ftm":0,"fta":0,"reb":3,"orb":1,"drb":2,"ast":6,"stl":1,"blk":0,"tov":2,"pf":2,"plus_minus":null},{"name":"Daryl McCoy","bart_id":14093,"is_starter":true,"mins":33,"pts":4,"fgm":2,"fga":6,"fgm3":0,"fga3":0,"ftm":0,"fta":0,"reb":9,"orb":5,"drb":4,"ast":3,"stl":0,"blk":0,"tov":5,"pf":5,"plus_minus":null},{"name":"Dartaye Ruffin","bart_id":19211,"is_starter":true,"mins":25,"pts":8,"fgm":4,"fga":6,"fgm3":0,"fga3":0,"ftm":0,"fta":1,"reb":6,"orb":4,"drb":2,"ast":0,"stl":1,"blk":0,"tov":1,"pf":4,"plus_minus":null},{"name":"Tavon Allen","bart_id":27687,"is_starter":true,"mins":6,"pts":0,"fgm":0,"fga":2,"fgm3":0,"fga3":0,"ftm":0,"fta":0,"reb":0,"orb":0,"drb":0,"ast":1,"stl":0,"blk":0,"tov":0,"pf":1,"plus_minus":null},{"name":"Damion Lee","bart_id":23228,"is_starter":false,"mins":36,"pts":26,"fgm":8,"fga":17,"fgm3":2,"fga3":7,"ftm":8,"fta":8,"reb":11,"orb":5,"drb":6,"ast":4,"stl":1,"blk":0,"tov":3,"pf":2,"plus_minus":null},{"name":"Kazembe Abif","bart_id":23296,"is_starter":false,"mins":18,"pts":6,"fgm":3,"fga":4,"fgm3":0,"fga3":0,"ftm":0,"fta":0,"reb":3,"orb":0,"drb":3,"ast":1,"stl":0,"blk":0,"tov":1,"pf":2,"plus_minus":null},{"name":"Goran Pantovic","bart_id":18333,"is_starter":false,"mins":5,"pts":2,"fgm":0,"fga":0,"fgm3":0,"fga3":0,"ftm":2,"fta":2,"reb":1,"orb":1,"drb":0,"ast":0,"stl":0,"blk":0,"tov":0,"pf":0,"plus_minus":null},{"name":"Aquil Younger","bart_id":23832,"is_starter":false,"mins":3,"pts":0,"fgm":0,"fga":0,"fgm3":0,"fga3":0,"ftm":0,"fta":0,"reb":0,"orb":0,"drb":0,"ast":0,"stl":0,"blk":0,"tov":0,"pf":0,"plus_minus":null}],"totals":{"fgm":26,"fga":53,"fgm3":5,"fga3":15,"ftm":12,"fta":13,"reb":35,"orb":16,"drb":19,"ast":18,"stl":3,"blk":0,"tov":13,"pf":17,"pts":69}}]}