{"cbba_game_id":1011314,"year":2019,"game_date":"2019-02-23","is_neutral":false,"teams":[{"name":"South Dakota","score":89,"players":[{"name":"Triston Simpson","bart_id":46816,"is_starter":true,"mins":40,"pts":19,"fgm":7,"fga":11,"fgm3":2,"fga3":5,"ftm":3,"fta":4,"reb":2,"orb":0,"drb":2,"ast":3,"stl":0,"blk":0,"tov":1,"pf":0,"plus_minus":null},{"name":"Cody Kelley","bart_id":41582,"is_starter":true,"mins":37,"pts":21,"fgm":7,"fga":10,"fgm3":5,"fga3":7,"ftm":2,"fta":2,"reb":3,"orb":0,"drb":3,"ast":4,"stl":0,"blk":0,"tov":3,"pf":5,"plus_minus":null},{"name":"Tyler Peterson","bart_id":46814,"is_starter":true,"mins":33,"pts":14,"fgm":6,"fga":7,"fgm3":0,"fga3":1,"ftm":2,"fta":2,"reb":3,"orb":0,"drb":3,"ast":0,"stl":0,"blk":0,"tov":1,"pf":4,"plus_minus":null},{"name":"Trey Burch-Manning","bart_id":46812,"is_starter":true,"mins":25,"pts":17,"fgm":6,"fga":12,"fgm3":3,"fga3":8,"ftm":2,"fta":4,"reb":6,"orb":2,"drb":4,"ast":2,"stl":0,"blk":0,"tov":4,"pf":4,"plus_minus":null},{"name":"Stanley Umude","bart_id":50918,"is_starter":true,"mins":25,"pts":7,"fgm":2,"fga":7,"fgm3":1,"fga3":2,"ftm":2,"fta":2,"reb":8,"orb":1,"drb":7,"ast":1,"stl":0,"blk":3,"tov":4,"pf":5,"plus_minus":null},{"name":"Brandon Armstrong","bart_id":46815,"is_starter":false,"mins":28,"pts":0,"fgm":0,"fga":4,"fgm3":0,"fga3":4,"ftm":0,"fta":0,"reb":2,"orb":0,"drb":2,"ast":5,"stl":0,"blk":0,"tov":1,"pf":3,"plus_minus":null},{"name":"Logan Power","bart_id":33735,"is_starter":false,"mins":12,"pts":11,"fgm":3,"fga":5,"fgm3":3,"fga3":5,"ftm":2,"fta":2,"reb":2,"orb":1,"drb":1,"ast":1,"stl":0,"blk":0,"tov":0,"pf":3,"plus_minus":null}],"totals":{"fgm":31,"fga":56,"fgm3":14,"fga3":32,"ftm":13,"fta":16,"reb":26,"orb":4,"drb":22,"ast":16,"stl":0,"blk":3,"tov":14,"pf":24,"pts":89}},{"name":"South Dakota St.","score":94,"players":[{"name":"Skyler Flatten","bart_id":36161,"is_starter":true,"mins":39,"pts":18,"fgm":6,"fga":10,"fgm3":4,"fga3":5,"ftm":2,"fta":2,"reb":7,"orb":0,"drb":7,"ast":3,"stl":2,"blk":0,"tov":2,"pf":2,"plus_minus":null},{"name":"David Jenkins Jr.","bart_id":51013,"is_starter":true,"mins":39,"pts":11,"fgm":2,"fga":8,"fgm3":0,"fga3":5,"ftm":7,"fta":9,"reb":4,"orb":0,"drb":4,"ast":2,"stl":1,"blk":0,"tov":2,"pf":1,"plus_minus":null},{"name":"Alex Arians","bart_id":66450,"is_starter":true,"mins":35,"pts":8,"fgm":4,"fga":7,"fgm3":0,"fga3":3,"ftm":0,"fta":0,"reb":3,"orb":0,"drb":3,"ast":2,"stl":1,"blk":0,"tov":0,"pf":2,"plus_minus":null},{"name":"Tevin King","bart_id":43156,"is_starter":true,"mins":32,"pts":22,"fgm":10,"fga":15,"fgm3":2,"fga3":4,"ftm":0,"fta":0,"reb":3,"orb":1,"drb":2,"ast":4,"stl":4,"blk":0,"tov":0,"pf":5,"plus_minus":null},{"name":"Mike Daum","bart_id":34839,"is_starter":true,"mins":30,"pts":25,"fgm":8,"fga":13,"fgm3":0,"fga3":2,"ftm":9,"fta":10,"reb":7,"orb":2,"drb":5,"ast":0,"stl":0,"blk":0,"tov":4,"pf":3,"plus_minus":null},{"name":"Owen King","bart_id":67825,"is_starter":false,"mins":20,"pts":8,"fgm":2,"fga":3,"fgm3":1,"fga3":1,"ftm":3,"fta":4,"reb":1,"orb":0,"drb":1,"ast":3,"stl":0,"blk":1,"tov":1,"pf":2,"plus_minus":null},{"name":"Matt Dentlinger","bart_id":66491,"is_starter":false,"mins":5,"pts":2,"fgm":0,"fga":1,"fgm3":0,"fga3":0,"ftm":2,"fta":2,"reb":3,"orb":2,"drb":1,"ast":0,"stl":0,"blk":0,"tov":0,"pf":1,"plus_minus":null}],"totals":{"fgm":32,"fga":57,"fgm3":7,"fga3":20,"ftm":23,"fta":27,"reb":28,"orb":5,"drb":23,"ast":14,"stl":8,"blk":1,"tov":9,"pf":16,"pts":94}}]}