{"cbba_game_id":1029547,"year":2019,"game_date":"2018-12-15","is_neutral":false,"teams":[{"name":"NJIT","score":90,"players":[{"name":"Diandre Wilson","bart_id":50645,"is_starter":true,"mins":36.9,"pts":12,"fgm":2,"fga":6,"fgm3":1,"fga3":3,"ftm":7,"fta":7,"reb":7,"orb":1,"drb":6,"ast":1,"stl":0,"blk":1,"tov":1,"pf":2,"plus_minus":10},{"name":"Abdul Lewis","bart_id":43816,"is_starter":true,"mins":36.8,"pts":20,"fgm":6,"fga":10,"fgm3":1,"fga3":1,"ftm":7,"fta":8,"reb":12,"orb":4,"drb":8,"ast":4,"stl":1,"blk":1,"tov":2,"pf":3,"plus_minus":10},{"name":"Zach Cooks","bart_id":50648,"is_starter":true,"mins":35.6,"pts":25,"fgm":7,"fga":13,"fgm3":5,"fga3":7,"ftm":6,"fta":6,"reb":7,"orb":0,"drb":7,"ast":0,"stl":2,"blk":0,"tov":3,"pf":4,"plus_minus":5},{"name":"Shyquan Gibbs","bart_id":45830,"is_starter":true,"mins":34.2,"pts":10,"fgm":3,"fga":3,"fgm3":0,"fga3":0,"ftm":4,"fta":5,"reb":0,"orb":0,"drb":0,"ast":4,"stl":1,"blk":0,"tov":1,"pf":3,"plus_minus":9},{"name":"San Antonio Brinson","bart_id":52003,"is_starter":true,"mins":32.5,"pts":18,"fgm":6,"fga":11,"fgm3":2,"fga3":5,"ftm":4,"fta":5,"reb":4,"orb":3,"drb":1,"ast":1,"stl":1,"blk":0,"tov":2,"pf":2,"plus_minus":15},{"name":"Diego Willis","bart_id":66201,"is_starter":false,"mins":8.6,"pts":0,"fgm":0,"fga":2,"fgm3":0,"fga3":1,"ftm":0,"fta":0,"reb":3,"orb":0,"drb":3,"ast":2,"stl":0,"blk":0,"tov":0,"pf":1,"plus_minus":7},{"name":"Mohamed Bendary","bart_id":38684,"is_starter":false,"mins":5.5,"pts":4,"fgm":1,"fga":3,"fgm3":0,"fga3":0,"ftm":2,"fta":2,"reb":0,"orb":0,"drb":0,"ast":0,"stl":0,"blk":0,"tov":1,"pf":4,"plus_minus":3},{"name":"Shawndale Jones","bart_id":50647,"is_starter":false,"mins":5.4,"pts":1,"fgm":0,"fga":1,"fgm3":0,"fga3":1,"ftm":1,"fta":2,"reb":0,"orb":0,"drb":0,"ast":0,"stl":0,"blk":0,"tov":0,"pf":0,"plus_minus":-10},{"name":"Donovan Greer","bart_id":48674,"is_starter":false,"mins":4.5,"pts":0,"fgm":0,"fga":1,"fgm3":0,"fga3":1,"ftm":0,"fta":0,"reb":0,"orb":0,"drb":0,"ast":0,"stl":0,"blk":0,"tov":1,"pf":0,"plus_minus":1}],"totals":{"fgm":25,"fga":50,"fgm3":9,"fga3":19,"ftm":31,"fta":35,"reb":33,"orb":8,"drb":25,"ast":12,"stl":5,"blk":2,"tov":11,"pf":19,"pts":90}},{"name":"Fairleigh Dickinson","score":80,"players":[{"name":"Jahlil Jenkins","bart_id":51091,"is_starter":true,"mins":39.4,"pts":16,"fgm":4,"fga":12,"fgm3":2,"fga3":6,"ftm":6,"fta":6,"reb":3,"orb":0,"drb":3,"ast":5,"stl":1,"blk":0,"tov":2,"pf":1,"plus_minus":-10},{"name":"Darnell Edge","bart_id":39322,"is_starter":true,"mins":38.7,"pts":16,"fgm":5,"fga":8,"fgm3":2,"fga3":5,"ftm":4,"fta":4,"reb":2,"orb":0,"drb":2,"ast":3,"stl":0,"blk":0,"tov":1,"pf":3,"plus_minus":-7},{"name":"Elyjah Williams","bart_id":50434,"is_starter":true,"mins":25.6,"pts":7,"fgm":2,"fga":4,"fgm3":0,"fga3":1,"ftm":3,"fta":5,"reb":4,"orb":2,"drb":2,"ast":2,"stl":1,"blk":0,"tov":2,"pf":4,"plus_minus":3},{"name":"Xzavier Malone-Key","bart_id":47772,"is_starter":true,"mins":23.5,"pts":6,"fgm":2,"fga":5,"fgm3":2,"fga3":4,"ftm":0,"fta":0,"reb":2,"orb":0,"drb":2,"ast":1,"stl":0,"blk":0,"tov":0,"pf":3,"plus_minus":-10},{"name":"Mike Holloway Jr.","bart_id":39688,"is_starter":true,"mins":19.7,"pts":10,"fgm":5,"fga":12,"fgm3":0,"fga3":1,"ftm":0,"fta":3,"reb":3,"orb":2,"drb":1,"ast":3,"stl":2,"blk":1,"tov":0,"pf":4,"plus_minus":-14},{"name":"Kaleb Bishop","bart_id":45479,"is_starter":false,"mins":34.2,"pts":16,"fgm":7,"fga":13,"fgm3":2,"fga3":4,"ftm":0,"fta":0,"reb":6,"orb":0,"drb":6,"ast":0,"stl":0,"blk":3,"tov":0,"pf":4,"plus_minus":-2},{"name":"Tyler Jones","bart_id":51092,"is_starter":false,"mins":7.8,"pts":3,"fgm":1,"fga":2,"fgm3":1,"fga3":2,"ftm":0,"fta":0,"reb":2,"orb":0,"drb":2,"ast":1,"stl":0,"blk":0,"tov":0,"pf":1,"plus_minus":-2},{"name":"Brandon Powell","bart_id":66328,"is_starter":false,"mins":7.2,"pts":4,"fgm":0,"fga":0,"fgm3":0,"fga3":0,"ftm":4,"fta":4,"reb":0,"orb":0,"drb":0,"ast":1,"stl":0,"blk":0,"tov":1,"pf":1,"plus_minus":-1},{"name":"Oscar Okeke","bart_id":67677,"is_starter":false,"mins":4,"pts":2,"fgm":1,"fga":2,"fgm3":0,"fga3":0,"ftm":0,"fta":0,"reb":1,"orb":1,"drb":0,"ast":0,"stl":0,"blk":0,"tov":1,"pf":2,"plus_minus":-7}],"totals":{"fgm":27,"fga":58,"fgm3":9,"fga3":23,"ftm":17,"fta":22,"reb":23,"orb":5,"drb":18,"ast":16,"stl":4,"blk":4,"tov":7,"pf":23,"pts":80}}]}