{"cbba_game_id":1256300,"year":2016,"game_date":"2016-02-27","is_neutral":false,"teams":[{"name":"Jackson St.","score":60,"players":[{"name":"Raeford Worsham","bart_id":27967,"is_starter":true,"mins":36,"pts":18,"fgm":7,"fga":15,"fgm3":0,"fga3":1,"ftm":4,"fta":5,"reb":15,"orb":7,"drb":8,"ast":3,"stl":3,"blk":2,"tov":4,"pf":1,"plus_minus":null},{"name":"Paris Collins","bart_id":40402,"is_starter":true,"mins":30,"pts":5,"fgm":2,"fga":12,"fgm3":1,"fga3":8,"ftm":0,"fta":0,"reb":3,"orb":0,"drb":3,"ast":2,"stl":2,"blk":0,"tov":5,"pf":1,"plus_minus":null},{"name":"Yettra Specks","bart_id":36767,"is_starter":true,"mins":28,"pts":11,"fgm":4,"fga":11,"fgm3":3,"fga3":7,"ftm":0,"fta":0,"reb":4,"orb":1,"drb":3,"ast":1,"stl":1,"blk":0,"tov":1,"pf":3,"plus_minus":null},{"name":"Treshawn Bolden","bart_id":31752,"is_starter":true,"mins":16,"pts":0,"fgm":0,"fga":3,"fgm3":0,"fga3":0,"ftm":0,"fta":0,"reb":8,"orb":1,"drb":7,"ast":3,"stl":0,"blk":2,"tov":3,"pf":2,"plus_minus":null},{"name":"Troy Stancil","bart_id":40414,"is_starter":true,"mins":10,"pts":0,"fgm":0,"fga":2,"fgm3":0,"fga3":1,"ftm":0,"fta":0,"reb":2,"orb":1,"drb":1,"ast":0,"stl":0,"blk":0,"tov":1,"pf":3,"plus_minus":null},{"name":"Javares Brent","bart_id":null,"cbba_player_id":1236247,"is_starter":false,"mins":29,"pts":6,"fgm":2,"fga":11,"fgm3":2,"fga3":11,"ftm":0,"fta":0,"reb":2,"orb":0,"drb":2,"ast":2,"stl":0,"blk":0,"tov":0,"pf":2,"plus_minus":null},{"name":"Janarius Middleton","bart_id":31749,"is_starter":false,"mins":24,"pts":9,"fgm":4,"fga":5,"fgm3":0,"fga3":0,"ftm":1,"fta":2,"reb":6,"orb":1,"drb":5,"ast":2,"stl":1,"blk":1,"tov":2,"pf":2,"plus_minus":null},{"name":"Kaven Bernard","bart_id":36754,"is_starter":false,"mins":18,"pts":11,"fgm":3,"fga":7,"fgm3":0,"fga3":1,"ftm":5,"fta":6,"reb":7,"orb":4,"drb":3,"ast":0,"stl":0,"blk":1,"tov":1,"pf":3,"plus_minus":null},{"name":"Dontaveon Robinson","bart_id":31747,"is_starter":false,"mins":8,"pts":0,"fgm":0,"fga":0,"fgm3":0,"fga3":0,"ftm":0,"fta":0,"reb":2,"orb":1,"drb":1,"ast":0,"stl":1,"blk":0,"tov":2,"pf":3,"plus_minus":null},{"name":"Jonathan Thomas","bart_id":19860,"is_starter":false,"mins":1,"pts":0,"fgm":0,"fga":0,"fgm3":0,"fga3":0,"ftm":0,"fta":0,"reb":0,"orb":0,"drb":0,"ast":0,"stl":0,"blk":0,"tov":0,"pf":0,"plus_minus":null}],"totals":{"fgm":22,"fga":66,"fgm3":6,"fga3":29,"ftm":10,"fta":13,"reb":49,"orb":16,"drb":33,"ast":13,"stl":8,"blk":6,"tov":19,"pf":20,"pts":60}},{"name":"Mississippi Valley St.","score":49,"players":[{"name":"John Sanders","bart_id":40754,"is_starter":true,"mins":28,"pts":10,"fgm":4,"fga":9,"fgm3":2,"fga3":5,"ftm":0,"fta":0,"reb":1,"orb":0,"drb":1,"ast":0,"stl":2,"blk":0,"tov":2,"pf":4,"plus_minus":null},{"name":"Vacha Vaughn","bart_id":29558,"is_starter":true,"mins":26,"pts":3,"fgm":1,"fga":9,"fgm3":0,"fga3":3,"ftm":1,"fta":2,"reb":12,"orb":1,"drb":11,"ast":2,"stl":1,"blk":0,"tov":0,"pf":2,"plus_minus":null},{"name":"Ta'Jay Henry","bart_id":40643,"is_starter":true,"mins":24,"pts":3,"fgm":1,"fga":8,"fgm3":0,"fga3":0,"ftm":1,"fta":3,"reb":5,"orb":3,"drb":2,"ast":0,"stl":2,"blk":0,"tov":0,"pf":2,"plus_minus":null},{"name":"Dwain Whitfield","bart_id":36218,"is_starter":true,"mins":18,"pts":0,"fgm":0,"fga":0,"fgm3":0,"fga3":0,"ftm":0,"fta":0,"reb":4,"orb":2,"drb":2,"ast":0,"stl":1,"blk":0,"tov":1,"pf":1,"plus_minus":null},{"name":"Latrell Love","bart_id":36227,"is_starter":true,"mins":12,"pts":0,"fgm":0,"fga":6,"fgm3":0,"fga3":0,"ftm":0,"fta":0,"reb":0,"orb":0,"drb":0,"ast":0,"stl":0,"blk":0,"tov":1,"pf":0,"plus_minus":null},{"name":"Marcus Romain","bart_id":43198,"is_starter":false,"mins":35,"pts":29,"fgm":8,"fga":17,"fgm3":3,"fga3":3,"ftm":10,"fta":14,"reb":6,"orb":4,"drb":2,"ast":0,"stl":1,"blk":1,"tov":5,"pf":1,"plus_minus":null},{"name":"Kylan Phillips","bart_id":40759,"is_starter":false,"mins":22,"pts":0,"fgm":0,"fga":3,"fgm3":0,"fga3":2,"ftm":0,"fta":0,"reb":0,"orb":0,"drb":0,"ast":1,"stl":0,"blk":0,"tov":4,"pf":2,"plus_minus":null},{"name":"Isaac Williams","bart_id":36228,"is_starter":false,"mins":14,"pts":0,"fgm":0,"fga":4,"fgm3":0,"fga3":3,"ftm":0,"fta":0,"reb":0,"orb":0,"drb":0,"ast":0,"stl":1,"blk":1,"tov":1,"pf":2,"plus_minus":null},{"name":"Jabari Alex","bart_id":35358,"is_starter":false,"mins":12,"pts":4,"fgm":2,"fga":3,"fgm3":0,"fga3":0,"ftm":0,"fta":0,"reb":5,"orb":1,"drb":4,"ast":0,"stl":0,"blk":0,"tov":0,"pf":1,"plus_minus":null},{"name":"Ronald Strother, Jr.","bart_id":40762,"is_starter":false,"mins":9,"pts":0,"fgm":0,"fga":1,"fgm3":0,"fga3":0,"ftm":0,"fta":0,"reb":0,"orb":0,"drb":0,"ast":0,"stl":1,"blk":2,"tov":1,"pf":0,"plus_minus":null}],"totals":{"fgm":16,"fga":60,"fgm3":5,"fga3":16,"ftm":12,"fta":19,"reb":33,"orb":11,"drb":22,"ast":3,"stl":9,"blk":4,"tov":15,"pf":15,"pts":49}}]}