{"cbba_game_id":1981337,"year":2022,"game_date":"2021-12-04","is_neutral":false,"teams":[{"name":"Boston University","score":68,"players":[{"name":"Javante McCoy","bart_id":50616,"is_starter":true,"mins":34.1,"pts":27,"fgm":11,"fga":17,"fgm3":4,"fga3":5,"ftm":1,"fta":2,"reb":7,"orb":1,"drb":6,"ast":3,"stl":3,"blk":1,"tov":3,"pf":1,"plus_minus":10},{"name":"Jonas Harper","bart_id":67520,"is_starter":true,"mins":30.3,"pts":9,"fgm":3,"fga":11,"fgm3":1,"fga3":9,"ftm":2,"fta":2,"reb":5,"orb":2,"drb":3,"ast":0,"stl":1,"blk":0,"tov":3,"pf":2,"plus_minus":8},{"name":"Sukhmail Mathon","bart_id":50617,"is_starter":true,"mins":29,"pts":16,"fgm":1,"fga":5,"fgm3":0,"fga3":1,"ftm":14,"fta":16,"reb":12,"orb":6,"drb":6,"ast":2,"stl":0,"blk":1,"tov":2,"pf":2,"plus_minus":3},{"name":"Fletcher Tynen","bart_id":66349,"is_starter":true,"mins":26.6,"pts":4,"fgm":1,"fga":3,"fgm3":0,"fga3":0,"ftm":2,"fta":2,"reb":7,"orb":1,"drb":6,"ast":0,"stl":0,"blk":0,"tov":1,"pf":2,"plus_minus":7},{"name":"Miles Brewster","bart_id":73841,"is_starter":true,"mins":23.2,"pts":3,"fgm":1,"fga":3,"fgm3":0,"fga3":2,"ftm":1,"fta":2,"reb":2,"orb":0,"drb":2,"ast":2,"stl":3,"blk":0,"tov":2,"pf":1,"plus_minus":10},{"name":"Anthony Morales","bart_id":73842,"is_starter":false,"mins":18.4,"pts":2,"fgm":1,"fga":3,"fgm3":0,"fga3":1,"ftm":0,"fta":1,"reb":4,"orb":3,"drb":1,"ast":1,"stl":1,"blk":1,"tov":1,"pf":2,"plus_minus":-3},{"name":"Garrett Pascoe","bart_id":66448,"is_starter":false,"mins":17.2,"pts":2,"fgm":1,"fga":3,"fgm3":0,"fga3":0,"ftm":0,"fta":0,"reb":1,"orb":0,"drb":1,"ast":2,"stl":0,"blk":0,"tov":1,"pf":3,"plus_minus":-6},{"name":"Malcolm Chimezie","bart_id":75476,"is_starter":false,"mins":11,"pts":2,"fgm":1,"fga":2,"fgm3":0,"fga3":0,"ftm":0,"fta":0,"reb":1,"orb":0,"drb":1,"ast":0,"stl":0,"blk":0,"tov":1,"pf":1,"plus_minus":2},{"name":"Caelan Jones","bart_id":73840,"is_starter":false,"mins":10.2,"pts":3,"fgm":1,"fga":3,"fgm3":1,"fga3":3,"ftm":0,"fta":0,"reb":0,"orb":0,"drb":0,"ast":0,"stl":0,"blk":0,"tov":0,"pf":1,"plus_minus":-6}],"totals":{"fgm":21,"fga":50,"fgm3":6,"fga3":21,"ftm":20,"fta":25,"reb":39,"orb":13,"drb":26,"ast":10,"stl":8,"blk":3,"tov":14,"pf":15,"pts":68}},{"name":"Binghamton","score":63,"players":[{"name":"Dan Petcash","bart_id":71675,"is_starter":true,"mins":35.3,"pts":11,"fgm":4,"fga":7,"fgm3":1,"fga3":2,"ftm":2,"fta":2,"reb":4,"orb":0,"drb":4,"ast":2,"stl":0,"blk":0,"tov":1,"pf":1,"plus_minus":-6},{"name":"Hakon Hjalmarsson","bart_id":71220,"is_starter":true,"mins":31,"pts":18,"fgm":7,"fga":10,"fgm3":4,"fga3":6,"ftm":0,"fta":0,"reb":3,"orb":1,"drb":2,"ast":3,"stl":2,"blk":0,"tov":3,"pf":4,"plus_minus":-5},{"name":"Tyler Bertram","bart_id":68103,"is_starter":true,"mins":30.9,"pts":14,"fgm":4,"fga":12,"fgm3":2,"fga3":6,"ftm":4,"fta":4,"reb":1,"orb":0,"drb":1,"ast":3,"stl":0,"blk":0,"tov":2,"pf":0,"plus_minus":-1},{"name":"George Tinsley","bart_id":71855,"is_starter":true,"mins":16.9,"pts":2,"fgm":1,"fga":4,"fgm3":0,"fga3":2,"ftm":0,"fta":0,"reb":2,"orb":0,"drb":2,"ast":0,"stl":1,"blk":0,"tov":2,"pf":2,"plus_minus":-8},{"name":"Taveion White","bart_id":70974,"is_starter":true,"mins":6.6,"pts":0,"fgm":0,"fga":0,"fgm3":0,"fga3":0,"ftm":0,"fta":0,"reb":1,"orb":0,"drb":1,"ast":0,"stl":0,"blk":0,"tov":0,"pf":4,"plus_minus":0},{"name":"Jacob Falko","bart_id":73118,"is_starter":false,"mins":24.7,"pts":6,"fgm":3,"fga":8,"fgm3":0,"fga3":1,"ftm":0,"fta":0,"reb":3,"orb":0,"drb":3,"ast":2,"stl":0,"blk":0,"tov":1,"pf":1,"plus_minus":-2},{"name":"Christian Hinckson","bart_id":65961,"is_starter":false,"mins":21.7,"pts":3,"fgm":0,"fga":2,"fgm3":0,"fga3":1,"ftm":3,"fta":4,"reb":3,"orb":1,"drb":2,"ast":2,"stl":1,"blk":1,"tov":1,"pf":2,"plus_minus":3},{"name":"Ogheneyole Akuwovo","bart_id":66550,"is_starter":false,"mins":17.1,"pts":4,"fgm":2,"fga":2,"fgm3":0,"fga3":0,"ftm":0,"fta":0,"reb":1,"orb":0,"drb":1,"ast":0,"stl":1,"blk":3,"tov":0,"pf":4,"plus_minus":-1},{"name":"Yarden Willis","bart_id":70902,"is_starter":false,"mins":9.6,"pts":3,"fgm":1,"fga":2,"fgm3":0,"fga3":0,"ftm":1,"fta":2,"reb":0,"orb":0,"drb":0,"ast":0,"stl":0,"blk":0,"tov":0,"pf":3,"plus_minus":1},{"name":"Bryce Beamer","bart_id":73322,"is_starter":false,"mins":6.2,"pts":2,"fgm":1,"fga":3,"fgm3":0,"fga3":1,"ftm":0,"fta":0,"reb":1,"orb":0,"drb":1,"ast":1,"stl":0,"blk":0,"tov":0,"pf":0,"plus_minus":-6}],"totals":{"fgm":23,"fga":50,"fgm3":7,"fga3":19,"ftm":10,"fta":12,"reb":19,"orb":2,"drb":17,"ast":13,"stl":5,"blk":4,"tov":10,"pf":21,"pts":63}}]}