{"cbba_game_id":1198137,"year":2017,"game_date":"2017-02-21","is_neutral":false,"teams":[{"name":"Mississippi St.","score":82,"players":[{"name":"Quinndary Weatherspoon","bart_id":41354,"is_starter":true,"mins":40,"pts":14,"fgm":7,"fga":14,"fgm3":0,"fga3":2,"ftm":0,"fta":0,"reb":8,"orb":3,"drb":5,"ast":4,"stl":4,"blk":1,"tov":2,"pf":4,"plus_minus":null},{"name":"I.J. Ready","bart_id":29654,"is_starter":true,"mins":39,"pts":20,"fgm":6,"fga":17,"fgm3":1,"fga3":3,"ftm":7,"fta":8,"reb":5,"orb":0,"drb":5,"ast":5,"stl":3,"blk":1,"tov":4,"pf":2,"plus_minus":null},{"name":"Mario Kegler","bart_id":48761,"is_starter":true,"mins":31,"pts":15,"fgm":6,"fga":11,"fgm3":1,"fga3":4,"ftm":2,"fta":2,"reb":8,"orb":3,"drb":5,"ast":1,"stl":2,"blk":0,"tov":4,"pf":5,"plus_minus":null},{"name":"Lamar Peters","bart_id":48760,"is_starter":true,"mins":26,"pts":3,"fgm":1,"fga":8,"fgm3":1,"fga3":6,"ftm":0,"fta":3,"reb":1,"orb":0,"drb":1,"ast":3,"stl":2,"blk":0,"tov":2,"pf":4,"plus_minus":null},{"name":"Schnider Herard","bart_id":46086,"is_starter":true,"mins":25,"pts":8,"fgm":3,"fga":5,"fgm3":0,"fga3":0,"ftm":2,"fta":7,"reb":4,"orb":3,"drb":1,"ast":0,"stl":0,"blk":1,"tov":2,"pf":3,"plus_minus":null},{"name":"Tyson Carter","bart_id":46089,"is_starter":false,"mins":24,"pts":8,"fgm":3,"fga":5,"fgm3":2,"fga3":3,"ftm":0,"fta":0,"reb":4,"orb":1,"drb":3,"ast":0,"stl":1,"blk":0,"tov":1,"pf":4,"plus_minus":null},{"name":"Xavian Stapleton","bart_id":35062,"is_starter":false,"mins":22,"pts":11,"fgm":4,"fga":10,"fgm3":0,"fga3":3,"ftm":3,"fta":3,"reb":9,"orb":3,"drb":6,"ast":0,"stl":1,"blk":2,"tov":1,"pf":5,"plus_minus":null},{"name":"Aric Holman","bart_id":41364,"is_starter":false,"mins":16,"pts":3,"fgm":1,"fga":4,"fgm3":1,"fga3":3,"ftm":0,"fta":2,"reb":3,"orb":2,"drb":1,"ast":0,"stl":0,"blk":2,"tov":3,"pf":4,"plus_minus":null},{"name":"E.J. Datcher","bart_id":46085,"is_starter":false,"mins":2,"pts":0,"fgm":0,"fga":0,"fgm3":0,"fga3":0,"ftm":0,"fta":0,"reb":0,"orb":0,"drb":0,"ast":0,"stl":0,"blk":0,"tov":2,"pf":1,"plus_minus":null}],"totals":{"fgm":31,"fga":74,"fgm3":6,"fga3":24,"ftm":14,"fta":25,"reb":42,"orb":15,"drb":27,"ast":13,"stl":13,"blk":7,"tov":21,"pf":32,"pts":82}},{"name":"Mississippi","score":87,"players":[{"name":"Terence Davis","bart_id":41358,"is_starter":true,"mins":38,"pts":12,"fgm":4,"fga":16,"fgm3":1,"fga3":6,"ftm":3,"fta":5,"reb":10,"orb":4,"drb":6,"ast":4,"stl":2,"blk":1,"tov":1,"pf":4,"plus_minus":null},{"name":"Sebastian Saiz","bart_id":32247,"is_starter":true,"mins":36,"pts":23,"fgm":6,"fga":11,"fgm3":0,"fga3":1,"ftm":11,"fta":11,"reb":10,"orb":4,"drb":6,"ast":0,"stl":2,"blk":1,"tov":5,"pf":4,"plus_minus":null},{"name":"Breein Tyree","bart_id":48763,"is_starter":true,"mins":36,"pts":24,"fgm":9,"fga":15,"fgm3":1,"fga3":2,"ftm":5,"fta":6,"reb":3,"orb":0,"drb":3,"ast":3,"stl":1,"blk":0,"tov":7,"pf":2,"plus_minus":null},{"name":"Deandre Burnett","bart_id":38553,"is_starter":true,"mins":35,"pts":10,"fgm":1,"fga":13,"fgm3":0,"fga3":9,"ftm":8,"fta":8,"reb":3,"orb":0,"drb":3,"ast":2,"stl":1,"blk":0,"tov":3,"pf":3,"plus_minus":null},{"name":"Marcanvis Hymon","bart_id":36837,"is_starter":true,"mins":32,"pts":4,"fgm":1,"fga":3,"fgm3":0,"fga3":0,"ftm":2,"fta":2,"reb":9,"orb":1,"drb":8,"ast":1,"stl":0,"blk":1,"tov":2,"pf":2,"plus_minus":null},{"name":"Cullen Neal","bart_id":47412,"is_starter":false,"mins":25,"pts":9,"fgm":3,"fga":7,"fgm3":3,"fga3":5,"ftm":0,"fta":0,"reb":3,"orb":1,"drb":2,"ast":0,"stl":1,"blk":0,"tov":2,"pf":1,"plus_minus":null},{"name":"Justas Furmanavicius","bart_id":48764,"is_starter":false,"mins":21,"pts":5,"fgm":0,"fga":0,"fgm3":0,"fga3":0,"ftm":5,"fta":12,"reb":4,"orb":1,"drb":3,"ast":0,"stl":1,"blk":3,"tov":1,"pf":4,"plus_minus":null},{"name":"Donte Fitzpatrick-Dorsey","bart_id":41352,"is_starter":false,"mins":2,"pts":0,"fgm":0,"fga":0,"fgm3":0,"fga3":0,"ftm":0,"fta":0,"reb":0,"orb":0,"drb":0,"ast":0,"stl":0,"blk":0,"tov":0,"pf":0,"plus_minus":null}],"totals":{"fgm":24,"fga":65,"fgm3":5,"fga3":23,"ftm":34,"fta":44,"reb":42,"orb":11,"drb":31,"ast":10,"stl":8,"blk":6,"tov":21,"pf":20,"pts":87}}]}